im_qsb/__init__.py
im_qsb-0.1.2.dist-info/DESCRIPTION.rst
im_qsb-0.1.2.dist-info/METADATA
im_qsb-0.1.2.dist-info/RECORD
im_qsb-0.1.2.dist-info/WHEEL
im_qsb-0.1.2.dist-info/metadata.json
im_qsb-0.1.2.dist-info/top_level.txt
